wls_analytics/__init__.py
wls_analytics/__main__.py
wls_analytics/config.py
wls_analytics/json2table.py
wls_analytics/utils.py
wls_analytics/commands/__init__.py
wls_analytics/commands/click_ext.py
wls_analytics/commands/log.py
wls_analytics/commands/outlog.py
wls_analytics/commands/wls_analytics.py
wls_analytics/log/__init__.py
wls_analytics/log/logreader.py
wls_analytics/log/outlog.py
wls_analytics-0.4.2.data/scripts/wlsanalytics
wls_analytics-0.4.2.dist-info/METADATA
wls_analytics-0.4.2.dist-info/WHEEL
wls_analytics-0.4.2.dist-info/entry_points.txt
wls_analytics-0.4.2.dist-info/top_level.txt
wls_analytics-0.4.2.dist-info/RECORD
