Metadata-Version: 2.1
Name: wls-analytics
Version: 0.4.2
Summary: WebLogic Analytics
Author: Tomas Vitvar
Author-email: tomas@vitvar.com
Classifier: Development Status :: 5 - Production/Stable
Classifier: Environment :: Console
Classifier: Intended Audience :: Developers
Classifier: Programming Language :: Python :: 3.11
Requires-Python: >=3.11.3
Requires-Dist: setuptools-scm >=6.3.2
Requires-Dist: click >=8.1.3
Requires-Dist: pyyaml >=6.0
Requires-Dist: tqdm >=4.62.3
